README
__init__.py
pyrsync.py
setup.py
pyrsync.egg-info/PKG-INFO
pyrsync.egg-info/SOURCES.txt
pyrsync.egg-info/dependency_links.txt
pyrsync.egg-info/top_level.txt