Metadata-Version: 1.1
Name: pyrsync
Version: 0.1.0
Summary: A Python module which implements rsync with SHA256 hash.
Home-page: https://github.com/isislovecruft/pyrsync
Author: Eric Pruitt, Isis Lovecruft
Author-email: isis@patternsinthevoid.net
License: ['MIT']
Platform: UNKNOWN
Classifier: Development Status :: 4 - Beta
Classifier: Environment :: Console
Classifier: Environment :: MacOS X
Classifier: Environment :: Win32 (MS Windows)
Classifier: Intended Audience :: Developers
Classifier: Intended Audience :: End Users/Desktop
Classifier: License :: OSI Approved :: MIT License
Classifier: Programming Language :: Python
Classifier: Topic :: Security :: Cryptography
Classifier: Topic :: Software Development :: Libraries :: Python Modules
Classifier: Topic :: System :: Archiving
Classifier: Topic :: System :: Archiving :: Backup
Classifier: Topic :: System :: Archiving :: Compression
